odoo/addons/account_reporting_weight/README.rst
odoo/addons/account_reporting_weight/__init__.py
odoo/addons/account_reporting_weight/__manifest__.py
odoo/addons/account_reporting_weight/i18n/account_reporting_weight.pot
odoo/addons/account_reporting_weight/i18n/de.po
odoo/addons/account_reporting_weight/i18n/es.po
odoo/addons/account_reporting_weight/i18n/fr.po
odoo/addons/account_reporting_weight/i18n/hr.po
odoo/addons/account_reporting_weight/i18n/hr_HR.po
odoo/addons/account_reporting_weight/i18n/id.po
odoo/addons/account_reporting_weight/i18n/it.po
odoo/addons/account_reporting_weight/i18n/pt_BR.po
odoo/addons/account_reporting_weight/i18n/sl.po
odoo/addons/account_reporting_weight/i18n/tr.po
odoo/addons/account_reporting_weight/readme/CONFIGURE.md
odoo/addons/account_reporting_weight/readme/CONTRIBUTORS.md
odoo/addons/account_reporting_weight/readme/DESCRIPTION.md
odoo/addons/account_reporting_weight/readme/INSTALL.md
odoo/addons/account_reporting_weight/readme/USAGE.md
odoo/addons/account_reporting_weight/reports/__init__.py
odoo/addons/account_reporting_weight/reports/account_invoice_report.py
odoo/addons/account_reporting_weight/static/description/icon.png
odoo/addons/account_reporting_weight/static/description/index.html
odoo_addon_account_reporting_weight-18.0.1.0.0.4.dist-info/METADATA
odoo_addon_account_reporting_weight-18.0.1.0.0.4.dist-info/WHEEL
odoo_addon_account_reporting_weight-18.0.1.0.0.4.dist-info/top_level.txt
odoo_addon_account_reporting_weight-18.0.1.0.0.4.dist-info/RECORD
